meiqian/__init__.py
meiqian/apis/__init__.py
meiqian/apis/weibo.py
meiqian/dm/__init__.py
meiqian/dm/dm.py
meiqian-0.0.2.dist-info/METADATA
meiqian-0.0.2.dist-info/WHEEL
meiqian-0.0.2.dist-info/top_level.txt
meiqian-0.0.2.dist-info/RECORD
