Metadata-Version: 2.1
Name: meiqian
Version: 0.0.2
Summary: 各种奇奇怪怪的功能
Author: meiqian
